{"name":"Cyprus","formal_name":"Republic of Cyprus","alpha2":"CY","alpha3":"CYP","numeric":196,"fips10":null,"geo_id":146669,"continent":"EU","parent":"WS","capital":146268,"borders":[],"demonym":null,"postal":"\\d{4}","phone":{"country_code":"357","international_prefix":"00","national_prefix":"","leading_digits":"","pattern":{"national":"(?:[279]\\d|[58]0)\\d{6}","fixed":"2[2-6]\\d{6}","mobile":"9[4-79]\\d{6}"}},"tld":["cy"],"language":[],"timezone":["Asia\/Famagusta","Asia\/Nicosia"],"currency":["EUR"],"is_eu":null,"is_un":null,"is_sovereign":false,"translation":{"en_US":"Cyprus","fr_FR":"Chypre","de_DE":"Zypern","es_ES":"Chipre","it_IT":"Cipro","pt_PT":"Chipre","ro_RO":"Cipru","zh_CN":"\u585e\u6d66\u8def\u65af","ja_JP":"\u30ad\u30d7\u30ed\u30b9","ko_KR":"\ud0a4\ud504\ub85c\uc2a4","ar_AE":"\u0642\u0628\u0631\u0635","ru_RU":"\u041a\u0438\u043f\u0440"}}