{"name":"Romania","formal_name":"Romania","alpha2":"RO","alpha3":"ROU","numeric":642,"fips10":null,"geo_id":798549,"continent":"EU","parent":"EE","capital":683506,"borders":["MD","HU","UA","BG","RS"],"demonym":null,"postal":"\\d{6}","phone":{"country_code":"40","international_prefix":"00","national_prefix":"0","leading_digits":"","pattern":{"national":"(?:[237]\\d|[89]0)\\d{7}|[23]\\d{5}","fixed":"[23][13-6]\\d{7}|(?:2(?:19\\d|[3-6]\\d9)|31\\d\\d)\\d\\d","mobile":"7[01]20\\d{5}|7(?:0[013-9]|1[01]|[2-7]\\d|8[03-8]|9[09])\\d{6}"}},"tld":["ro"],"language":[],"timezone":["Europe\/Bucharest"],"currency":["RON"],"is_eu":null,"is_un":null,"is_sovereign":false,"translation":{"en_US":"Romania","fr_FR":"Roumanie","de_DE":"Rum\u00e4nien","es_ES":"Ruman\u00eda","it_IT":"Romania","pt_PT":"Rom\u00eania","ro_RO":"Rom\u00e2nia","zh_CN":"\u7f57\u9a6c\u5c3c\u4e9a","ja_JP":"\u30eb\u30fc\u30de\u30cb\u30a2","ko_KR":"\ub8e8\ub9c8\ub2c8\uc544","ar_AE":"\u0631\u0648\u0645\u0627\u0646\u064a\u0627","ru_RU":"\u0420\u0443\u043c\u044b\u043d\u0438\u044f"}}