{"name":"South Sudan","formal_name":"Republic of South Sudan","alpha2":"SS","alpha3":"SSD","numeric":728,"fips10":null,"geo_id":7909807,"continent":"AF","parent":"EF","capital":373303,"borders":["CD","CF","ET","KE","SD","UG"],"demonym":null,"postal":null,"phone":{"country_code":"211","international_prefix":"00","national_prefix":"0","leading_digits":"","pattern":{"national":"[19]\\d{8}","fixed":"1[89]\\d{7}","mobile":"(?:12|9[12579])\\d{7}"}},"tld":["ss"],"language":[],"timezone":["Africa\/Juba"],"currency":["SSP"],"is_eu":null,"is_un":null,"is_sovereign":false,"translation":{"en_US":"South Sudan","fr_FR":"Soudan du Sud","de_DE":"S\u00fcdsudan","es_ES":"Sud\u00e1n del Sur","it_IT":"Sud Sudan","pt_PT":"Sud\u00e3o do Sul","ro_RO":"Sudanul de Sud","zh_CN":"\u5357\u82cf\u4e39","ja_JP":"\u5357\u30b9\u30fc\u30c0\u30f3","ko_KR":"\ub0a8\uc218\ub2e8","ar_AE":"\u062c\u0646\u0648\u0628 \u0627\u0644\u0633\u0648\u062f\u0627\u0646","ru_RU":"\u042e\u0436\u043d\u044b\u0439 \u0421\u0443\u0434\u0430\u043d"}}